pymodaq_plugins_picoquant/__init__.py
pymodaq_plugins_picoquant/utils.py
pymodaq_plugins_picoquant/daq_move_plugins/__init__.py
pymodaq_plugins_picoquant/daq_viewer_plugins/__init__.py
pymodaq_plugins_picoquant/daq_viewer_plugins/plugins_1D/__init__.py
pymodaq_plugins_picoquant/daq_viewer_plugins/plugins_1D/daq_1Dviewer_TH260.py
pymodaq_plugins_picoquant/hardware/__init__.py
pymodaq_plugins_picoquant/hardware/utils.py
pymodaq_plugins_picoquant/hardware/picoquant/__init__.py
pymodaq_plugins_picoquant/hardware/picoquant/histomode.out
pymodaq_plugins_picoquant/hardware/picoquant/histomode.py
pymodaq_plugins_picoquant/hardware/picoquant/timeharp260.py
pymodaq_plugins_picoquant/hardware/picoquant/tttrmode.py
pymodaq_plugins_picoquant/hardware/picoquant/cython/__init__.py
pymodaq_plugins_picoquant/hardware/picoquant/cython/cth260defin.pxd
pymodaq_plugins_picoquant/hardware/picoquant/cython/cth260lib.pxd
pymodaq_plugins_picoquant/hardware/picoquant/cython/setup.py
pymodaq_plugins_picoquant/hardware/picoquant/cython/th260defin.h
pymodaq_plugins_picoquant/hardware/picoquant/cython/th260lib.c
pymodaq_plugins_picoquant/hardware/picoquant/cython/th260lib.h
pymodaq_plugins_picoquant/hardware/picoquant/cython/th260lib.pyx
pymodaq_plugins_picoquant/hardware/picoquant/cython/th260lib64.dll
pymodaq_plugins_picoquant/hardware/picoquant/cython/th260lib64.lib
pymodaq_plugins_picoquant/hardware/picoquant/tttr_cython/__init__.py
pymodaq_plugins_picoquant/hardware/picoquant/tttr_cython/setup.py
pymodaq_plugins_picoquant/hardware/picoquant/tttr_cython/tttr.c
pymodaq_plugins_picoquant/hardware/picoquant/tttr_cython/tttr.pyx
pymodaq_plugins_picoquant/hardware/picoquant/tttr_cython/tttr_test.py
pymodaq_plugins_picoquant/resources/__init__.py
pymodaq_plugins_picoquant/resources/config_template.toml
pymodaq_plugins_picoquant-5.0.1.dist-info/METADATA
pymodaq_plugins_picoquant-5.0.1.dist-info/WHEEL
pymodaq_plugins_picoquant-5.0.1.dist-info/entry_points.txt
pymodaq_plugins_picoquant-5.0.1.dist-info/licenses/LICENSE
pymodaq_plugins_picoquant-5.0.1.dist-info/RECORD
